fluidly_fastapi-0.1.6-py3.7-nspkg.pth
fluidly/fastapi/__init__.py
fluidly/fastapi/py.typed
fluidly/fastapi/utils.py
fluidly/fastapi/constants/__init__.py
fluidly/fastapi/constants/status.py
fluidly/fastapi/dependencies/__init__.py
fluidly/fastapi/dependencies/auth.py
fluidly/fastapi/middleware/__init__.py
fluidly/fastapi/middleware/logging.py
fluidly/fastapi/responses/__init__.py
fluidly/fastapi/responses/health.py
fluidly/fastapi/responses/readiness.py
fluidly/fastapi/responses/uptime.py
fluidly_fastapi-0.1.6.dist-info/METADATA
fluidly_fastapi-0.1.6.dist-info/WHEEL
fluidly_fastapi-0.1.6.dist-info/namespace_packages.txt
fluidly_fastapi-0.1.6.dist-info/top_level.txt
fluidly_fastapi-0.1.6.dist-info/RECORD
