Metadata-Version: 2.1
Name: fluidly-fastapi
Version: 0.1.6
Summary: Fastapi helpers.
Home-page: https://github.com/fluidly/python-shared
Author: Fluidly
Author-email: tech@fluidly.com
License: UNKNOWN
Platform: UNKNOWN
Requires-Python: >=3.6.0
Requires-Dist: fastapi (==0.68.2)
Requires-Dist: fastapi-camelcase
Requires-Dist: fluidly-structlog
Requires-Dist: fluidly-auth
